dash_pathway/__init__.py
dash_pathway-0.0.3.dist-info/LICENSE
dash_pathway-0.0.3.dist-info/METADATA
dash_pathway-0.0.3.dist-info/WHEEL
dash_pathway-0.0.3.dist-info/top_level.txt
dash_pathway-0.0.3.dist-info/RECORD
