Metadata-Version: 2.1
Name: dash-pathway
Version: 0.0.3
Summary: UNKNOWN
Home-page: UNKNOWN
Author: UNKNOWN
Author-email: UNKNOWN
License: UNKNOWN
Platform: UNKNOWN
Requires-Dist: dash-cytoscape
Requires-Dist: dash
Requires-Dist: pathway2cyjs
